numira/__init__.py
numira-0.1.0.dist-info/METADATA
numira-0.1.0.dist-info/WHEEL
numira-0.1.0.dist-info/top_level.txt
numira-0.1.0.dist-info/RECORD
