Metadata-Version: 2.4
Name: numira
Version: 0.1.0
Summary: A toolbox for math experimentation
Home-page: https://github.com/ZT-devinci/numira
Author: ZT_Production
Author-email: zhenting37@gmail.com
Classifier: Programming Language :: Python :: 3
Classifier: License :: OSI Approved :: MIT License
Dynamic: author
Dynamic: author-email
Dynamic: classifier
Dynamic: description
Dynamic: description-content-type
Dynamic: home-page
Dynamic: summary
